fireblocks_sdk/__init__.py
fireblocks_sdk/api_types.py
fireblocks_sdk/ncw_sdk.py
fireblocks_sdk/sdk.py
fireblocks_sdk/sdk_token_provider.py
fireblocks_sdk/tokenization_api_types.py
fireblocks_sdk-2.16.0.dist-info/licenses/LICENSE.txt
fireblocks_sdk-2.16.0.dist-info/METADATA
fireblocks_sdk-2.16.0.dist-info/WHEEL
fireblocks_sdk-2.16.0.dist-info/top_level.txt
fireblocks_sdk-2.16.0.dist-info/RECORD
